pm/__init__.py
pm/cli/__init__.py
pm/cli/__main__.py
pm/cli/base.py
pm/cli/common_utils.py
pm/cli/constants.py
pm/cli/guideline/__init__.py
pm/cli/guideline/copy.py
pm/cli/guideline/create.py
pm/cli/guideline/delete.py
pm/cli/guideline/list.py
pm/cli/guideline/main.py
pm/cli/guideline/show.py
pm/cli/guideline/update.py
pm/cli/guideline/utils.py
pm/cli/init.py
pm/cli/note/__init__.py
pm/cli/note/add.py
pm/cli/note/delete.py
pm/cli/note/list.py
pm/cli/note/main.py
pm/cli/note/show.py
pm/cli/note/update.py
pm/cli/project/__init__.py
pm/cli/project/create.py
pm/cli/project/delete.py
pm/cli/project/list.py
pm/cli/project/main.py
pm/cli/project/show.py
pm/cli/project/tasks.py
pm/cli/project/update.py
pm/cli/project/utils.py
pm/cli/task/__init__.py
pm/cli/task/create.py
pm/cli/task/delete.py
pm/cli/task/dependency.py
pm/cli/task/list.py
pm/cli/task/main.py
pm/cli/task/metadata/__init__.py
pm/cli/task/metadata/delete.py
pm/cli/task/metadata/get.py
pm/cli/task/metadata/main.py
pm/cli/task/metadata/query.py
pm/cli/task/metadata/set.py
pm/cli/task/show.py
pm/cli/task/subtask/__init__.py
pm/cli/task/subtask/create.py
pm/cli/task/subtask/delete.py
pm/cli/task/subtask/list.py
pm/cli/task/subtask/main.py
pm/cli/task/subtask/show.py
pm/cli/task/subtask/update.py
pm/cli/task/update.py
pm/cli/template/__init__.py
pm/cli/template/add_subtask.py
pm/cli/template/apply.py
pm/cli/template/create.py
pm/cli/template/delete.py
pm/cli/template/list.py
pm/cli/template/main.py
pm/cli/template/show.py
pm/cli/welcome.py
pm/core/__init__.py
pm/core/config.py
pm/core/constants.py
pm/core/guideline.py
pm/core/types.py
pm/core/utils.py
pm/models/__init__.py
pm/models/metadata.py
pm/models/note.py
pm/models/project.py
pm/models/subtask.py
pm/models/task.py
pm/models/template.py
pm/resources/welcome_guidelines_coding.md
pm/resources/welcome_guidelines_pm.md
pm/resources/welcome_guidelines_testing.md
pm/resources/welcome_guidelines_vcs.md
pm/storage/__init__.py
pm/storage/db.py
pm/storage/metadata.py
pm_tool-0.3.1.dist-info/WHEEL
pm_tool-0.3.1.dist-info/entry_points.txt
pm_tool-0.3.1.dist-info/METADATA
pm_tool-0.3.1.dist-info/RECORD
