Metadata-Version: 2.4
Name: pm-tool
Version: 0.3.1
Summary: Project management CLI for AI assistants
Keywords: cli,project management,task management,ai,assistant,developer tools
Author: metulah
Author-email: metulah <metulah@proton.me>
License-Expression: MIT
Classifier: Development Status :: 3 - Alpha
Classifier: Environment :: Console
Classifier: Intended Audience :: Developers
Classifier: Operating System :: OS Independent
Classifier: Programming Language :: Python :: 3
Classifier: Programming Language :: Python :: 3.10
Classifier: Programming Language :: Python :: 3.11
Classifier: Programming Language :: Python :: 3.12
Classifier: Programming Language :: Python :: 3.13
Classifier: Topic :: Software Development :: Build Tools
Classifier: Topic :: Software Development :: Bug Tracking
Classifier: Topic :: Utilities
Requires-Dist: click>=8.0.0
Requires-Dist: python-frontmatter>=1.0.0
Requires-Dist: sqlalchemy>=2.0.0
Requires-Dist: toml>=0.10.2
Requires-Dist: pytest>=7.0.0 ; extra == 'dev'
Requires-Dist: black>=23.0.0 ; extra == 'dev'
Requires-Dist: isort>=5.0.0 ; extra == 'dev'
Requires-Dist: ruff>=0.1.0 ; extra == 'dev'
Requires-Dist: build>=1.2 ; extra == 'publish'
Requires-Dist: twine>=6.1 ; extra == 'publish'
Requires-Python: >=3.10
Project-URL: Homepage, https://github.com/metulah/pm
Project-URL: Repository, https://github.com/metulah/pm
Provides-Extra: dev
Provides-Extra: publish
